booleans/__init__.py
booleans/booleans.py
booleans-0.1.0.dist-info/licenses/LICENSE
booleans-0.1.0.dist-info/METADATA
booleans-0.1.0.dist-info/WHEEL
booleans-0.1.0.dist-info/top_level.txt
booleans-0.1.0.dist-info/RECORD
