Metadata-Version: 2.4
Name: Booleans
Version: 0.1.0
Summary: A micro-library for returning boolean values explicitly with Booleans.true() and Booleans.false().
Author-email: Bittu Singh <bittusinghtech@gmail.com>
License: MIT
Classifier: Programming Language :: Python :: 3
Classifier: License :: OSI Approved :: MIT License
Classifier: Operating System :: OS Independent
Requires-Python: >=3.7
License-File: LICENSE
Dynamic: license-file
